pyneato/__init__.py
pyneato/account.py
pyneato/enum.py
pyneato/exception.py
pyneato/floorplan.py
pyneato/neato.py
pyneato/robot.py
pyneato/robot_state.py
pyneato/session.py
pyneato/version.py
pyneato-0.0.8.dist-info/METADATA
pyneato-0.0.8.dist-info/WHEEL
pyneato-0.0.8.dist-info/licenses/LICENSE
pyneato-0.0.8.dist-info/RECORD
