Metadata-Version: 2.1
Name: pyneato
Version: 0.0.8
Summary: Package to control a neato vacuum robot
Author-email: Benjamin Paap <benjamin.paap@gmail.com>
License-File: LICENSE
Classifier: License :: OSI Approved :: MIT License
Classifier: Operating System :: OS Independent
Classifier: Programming Language :: Python :: 3
Requires-Python: >=3.7
